{
  "name": "XMediatorAppLovin",
  "version": "13.5.1.3",
  "summary": "XMediator AppLovin Adapter",
  "description": "XMediator AppLovin Adapter.",
  "homepage": "https://x3mads.com/",
  "license": {
    "type": "Commercial",
    "text": "https://x3mads.com/terms"
  },
  "authors": "X3M",
  "static_framework": true,
  "platforms": {
    "ios": "13.0"
  },
  "swift_versions": "5.0",
  "cocoapods_version": ">= 1.13.0",
  "dependencies": {
    "XMediator": [
      "~> 1.139"
    ],
    "AppLovinSDK": [
      "13.5.1"
    ]
  },
  "source": {
    "http": "https://ios-artifact-registry.x3mads.com/cocoapods/XMediatorAppLovin/XMediatorAppLovin-13.5.1.3.zip"
  },
  "vendored_frameworks": "XMediatorAppLovin.xcframework",
  "swift_version": "5.0"
}
